ShenghuaGuancaiQuantuiWenji2020112/README.md
ShenghuaGuancaiQuantuiWenji2020112/__init__.py
ShenghuaGuancaiQuantuiWenji2020112/__main__.py
ShenghuaGuancaiQuantuiWenji2020112/file.epub
ShenghuaGuancaiQuantuiWenji2020112/index.html
ShenghuaGuancaiQuantuiWenji2020112/css/__init__.py
ShenghuaGuancaiQuantuiWenji2020112/css/annotations.css
ShenghuaGuancaiQuantuiWenji2020112/css/main.css
ShenghuaGuancaiQuantuiWenji2020112/css/normalize.css
ShenghuaGuancaiQuantuiWenji2020112/css/popup.css
ShenghuaGuancaiQuantuiWenji2020112/font/__init__.py
ShenghuaGuancaiQuantuiWenji2020112/font/fontello.eot
ShenghuaGuancaiQuantuiWenji2020112/font/fontello.svg
ShenghuaGuancaiQuantuiWenji2020112/font/fontello.ttf
ShenghuaGuancaiQuantuiWenji2020112/font/fontello.woff
ShenghuaGuancaiQuantuiWenji2020112/img/__init__.py
ShenghuaGuancaiQuantuiWenji2020112/img/annotator-glyph-sprite.png
ShenghuaGuancaiQuantuiWenji2020112/img/annotator-icon-sprite.png
ShenghuaGuancaiQuantuiWenji2020112/img/apple-touch-icon.png
ShenghuaGuancaiQuantuiWenji2020112/img/cancelfullscreen.png
ShenghuaGuancaiQuantuiWenji2020112/img/close.png
ShenghuaGuancaiQuantuiWenji2020112/img/fullscreen.png
ShenghuaGuancaiQuantuiWenji2020112/img/loader.gif
ShenghuaGuancaiQuantuiWenji2020112/img/menu-icon.png
ShenghuaGuancaiQuantuiWenji2020112/img/save.png
ShenghuaGuancaiQuantuiWenji2020112/img/saved.png
ShenghuaGuancaiQuantuiWenji2020112/img/settings-s.png
ShenghuaGuancaiQuantuiWenji2020112/img/settings.png
ShenghuaGuancaiQuantuiWenji2020112/img/star.png
ShenghuaGuancaiQuantuiWenji2020112/js/__init__.py
ShenghuaGuancaiQuantuiWenji2020112/js/epub.js
ShenghuaGuancaiQuantuiWenji2020112/js/epub.min.js
ShenghuaGuancaiQuantuiWenji2020112/js/epub.min.map
ShenghuaGuancaiQuantuiWenji2020112/js/hooks.min.js
ShenghuaGuancaiQuantuiWenji2020112/js/hooks.min.map
ShenghuaGuancaiQuantuiWenji2020112/js/reader.js
ShenghuaGuancaiQuantuiWenji2020112/js/reader.js.map
ShenghuaGuancaiQuantuiWenji2020112/js/reader.min.js
shenghua_guancai_quantui_wenji_2020_11_2-2024.3.5.0.dist-info/METADATA
shenghua_guancai_quantui_wenji_2020_11_2-2024.3.5.0.dist-info/WHEEL
shenghua_guancai_quantui_wenji_2020_11_2-2024.3.5.0.dist-info/entry_points.txt
shenghua_guancai_quantui_wenji_2020_11_2-2024.3.5.0.dist-info/top_level.txt
shenghua_guancai_quantui_wenji_2020_11_2-2024.3.5.0.dist-info/RECORD
